[
  {
    "name": "Chapter 1: Chapter One",
    "url": "https://raw.githack.com/hanubhaiji/newda_hin_3/main/cha50/Maya%20and%20the%20Rising%20Dark_Part_01.mp3"
  },
  {
    "name": "Chapter 2: Chapter Two",
    "url": "https://raw.githack.com/hanubhaiji/newda_hin_3/main/cha50/Maya%20and%20the%20Rising%20Dark_Part_02.mp3"
  },
  {
    "name": "Chapter 3: Chapter Three",
    "url": "https://raw.githack.com/hanubhaiji/newda_hin_3/main/cha50/Maya%20and%20the%20Rising%20Dark_Part_03.mp3"
  },
  {
    "name": "Chapter 4: Chapter Four",
    "url": "https://raw.githack.com/hanubhaiji/newda_hin_3/main/cha50/Maya%20and%20the%20Rising%20Dark_Part_04.mp3"
  },
  {
    "name": "Chapter 5: Chapter Five",
    "url": "https://raw.githack.com/hanubhaiji/newda_hin_3/main/cha50/Maya%20and%20the%20Rising%20Dark_Part_05.mp3"
  },
  {
    "name": "Chapter 6: Chapter Six",
    "url": "https://raw.githack.com/hanubhaiji/newda_hin_3/main/cha50/Maya%20and%20the%20Rising%20Dark_Part_06.mp3"
  }
]